CheeseAPI/__init__.py
CheeseAPI/app.py
CheeseAPI/cors.py
CheeseAPI/file.py
CheeseAPI/printer.py
CheeseAPI/request.py
CheeseAPI/response.py
CheeseAPI/route.py
CheeseAPI/scheduler.py
CheeseAPI/signal.py
CheeseAPI/validator.py
CheeseAPI/websocket.py
cheeseapi-2.0.0.dist-info/METADATA
cheeseapi-2.0.0.dist-info/WHEEL
cheeseapi-2.0.0.dist-info/licenses/LICENSE
cheeseapi-2.0.0.dist-info/RECORD
