Metadata-Version: 2.4
Name: CheeseAPI
Version: 2.0.0
Summary: 一款web协程框架
Project-URL: Source, https://github.com/CheeseUnknown/CheeseAPI
Author-email: Cheese Unknown <cheese@cheese.ren>
License-File: LICENSE
Keywords: API,BackEnd
Requires-Dist: brotli
Requires-Dist: cheeselog==2.1.*
Requires-Dist: cheesesignal==2.1.*
Requires-Dist: psutil
Requires-Dist: pydantic
Requires-Dist: redis
Requires-Dist: zstandard
Provides-Extra: dev
Requires-Dist: requests; extra == 'dev'
Requires-Dist: websockets; extra == 'dev'
